coco_experiment-2.8.1.dist-info/METADATA
coco_experiment-2.8.1.dist-info/WHEEL
cocoex/interface.cp310-win_amd64.pyd
cocoex/interface.cp310-win_amd64.lib
cocoex/bare_problem.cp310-win_amd64.pyd
cocoex/bare_problem.cp310-win_amd64.lib
cocoex/__init__.py
cocoex/_version.py
cocoex/download_example.py
cocoex/exceptions.py
cocoex/noiser.py
cocoex/solvers.py
cocoex/utilities.py
coco_experiment-2.8.1.dist-info/RECORD
