Metadata-Version: 2.4
Name: coco-experiment
Version: 2.8.1
Summary: Benchmarking framework for all types of black-box optimization algorithms.
Project-URL: Homepage, https://github.com/numbbo/coco-experiment
Project-URL: Documentation, https://numbbo.github.io/coco-doc/apidocs/cocoex/
Project-URL: Issues, https://github.com/numbbo/coco-experiment/issues
Author: Asma Atamna, Dimo Brockhoff, Lorenzo Consoli, Ouassim Ait ElHara, Paul Dufossé, Nikolaus Hansen, Leopold Luley, Olaf Mersmann, Duc Manh Nguyen, Phillipe R. Sampaio, Marc Schoenauer, Dejan Tušar, Tea Tušar, Konstantinos Varelas
License: BSD-3-Clause
License-File: LICENSE
Classifier: Development Status :: 4 - Beta
Classifier: License :: OSI Approved :: BSD License
Classifier: Programming Language :: Python
Classifier: Programming Language :: Python :: 3.8
Classifier: Programming Language :: Python :: 3.9
Classifier: Programming Language :: Python :: 3.10
Classifier: Programming Language :: Python :: 3.11
Classifier: Programming Language :: Python :: 3.12
Classifier: Programming Language :: Python :: Implementation :: CPython
Requires-Python: >=3.8
Requires-Dist: numpy>=1.24.0
